{
  "transaction": [
    {
      "id": "1",
      "description": "Test Transaction",
      "type": "income",
      "category": "venda",
      "price": 12400,
      "createAt": "2020-07-29T19:30:44.5052"
    },
    {
      "id": "2",
      "description": "Test negative Transaction",
      "type": "outcome",
      "category": "alimento",
      "price": 900,
      "createAt": "2020-04-29T19:30:44.5052"
    },
    {
      "id": "3",
      "description": "Ignite",
      "type": "outcome",
      "category": "educação",
      "price": 112,
      "createAt": "2020-04-29T19:30:44.5052"
    }
  ]
}